yourgoal
