Metadata-Version: 2.1
Name: yourgoal
Version: 1.0
Summary: 为定目标的创立的程序。
Home-page: https://www.bilibili.com/video/BV1GJ411x7h7/
Author: 小松果
Author-email: aaron.dongsq@hotmail.com
Maintainer: 小松果
Maintainer-email: aaron.dongsq@hotmail.com
